data_structures/__init__.py
data_structures/graphs/__init__.py
data_structures/graphs/graphs.py
data_structures/graphs/vertex.py
data_structures/trees/__init__.py
data_structures/trees/binary_tree.py
data_structures/trees/simple_tree.py
core_data_structures-1.1.0.dist-info/LICENSE
core_data_structures-1.1.0.dist-info/METADATA
core_data_structures-1.1.0.dist-info/WHEEL
core_data_structures-1.1.0.dist-info/top_level.txt
core_data_structures-1.1.0.dist-info/RECORD
